ocrdownloader2/__init__.py
ocrdownloader2/cli.py
ocrdownloader2/crawler.py
ocrdownloader2/data/__init__.py
ocrdownloader2/data/author.py
ocrdownloader2/data/track.py
ocrdownloader2/downloader.py
ocrdownloader2/downloaders/__init__.py
ocrdownloader2/downloaders/aria2_downloader.py
ocrdownloader2/downloaders/downloader.py
ocrdownloader2-2.0.2.dist-info/entry_points.txt
ocrdownloader2-2.0.2.dist-info/WHEEL
ocrdownloader2-2.0.2.dist-info/METADATA
ocrdownloader2-2.0.2.dist-info/RECORD
